sh_mod_loader/__init__.py
sh_mod_loader/mod_loader.py
sh_mod_loader-0.4.0.dist-info/licenses/LICENSE
sh_mod_loader-0.4.0.dist-info/METADATA
sh_mod_loader-0.4.0.dist-info/WHEEL
sh_mod_loader-0.4.0.dist-info/top_level.txt
sh_mod_loader-0.4.0.dist-info/RECORD
