Metadata-Version: 2.4
Name: sh_mod_loader
Version: 0.4.0
Summary: Simple ModLoader for Python
Home-page: https://github.com/SeniorShadifer/MyModLoader
Author: SeniorShadifer
License-Expression: MIT
Project-URL: Homepage, https://github.com/SeniorShadifer/MyModLoader
Project-URL: Issues, https://github.com/SeniorShadifer/MyModLoader/issues
Classifier: Programming Language :: Python :: 3
Classifier: Operating System :: OS Independent
Requires-Python: >=3.6
License-File: LICENSE
Dynamic: home-page
Dynamic: license-file
Dynamic: requires-python
